regexplain-0.1.0a16.dist-info/METADATA
regexplain-0.1.0a16.dist-info/WHEEL
regexplain-0.1.0a16.dist-info/entry_points.txt
regexplain-0.1.0a16.dist-info/licenses/LICENSE
regexplain/__init__.py
regexplain/builder.py
regexplain/builder_bkp.py
regexplain/tokenizer/__init__.py
regexplain/tokenizer/base.py
regexplain/tokenizer/grouped.py
regexplain/tokenizer/non_grouped.py
regexplain/tokenizer/root.py
regexplain/utils.py
regexplain/version.py
regexplain-0.1.0a16.dist-info/RECORD
