Metadata-Version: 2.1
Name: regexplain
Version: 0.1.0a16
Summary: Build and explain Python Regex patterns in a human-friendly way
Keywords: regex
Author-Email: "Aalap Shah (aka fishfin)" <shah.aalap@gmail.com>
License: MIT License
Classifier: Development Status :: 2 - Pre-Alpha
Classifier: Intended Audience :: Developers
Classifier: License :: OSI Approved :: MIT License
Classifier: Operating System :: OS Independent
Classifier: Programming Language :: Python :: 3
Classifier: Programming Language :: Python :: 3 :: Only
Classifier: Programming Language :: Python :: 3.10
Classifier: Programming Language :: Python :: 3.11
Classifier: Programming Language :: Python :: 3.12
Classifier: Programming Language :: Python :: 3.13
Classifier: Programming Language :: Python :: 3.14
Classifier: Topic :: Software Development
Classifier: Topic :: Utilities
Project-URL: Homepage, https://gitlab.com/shah-aalap/python-regexplain
Requires-Python: >=3.10
Requires-Dist: pyyaml>=6.0.2
